LICENSE
MANIFEST.in
README.rst
setup.py
itunesiap/__init__.py
itunesiap/core.py
itunesiap/exceptions.py
itunesiap/shortcut.py
itunesiap/version.txt
tsl_itunes_iap.egg-info/PKG-INFO
tsl_itunes_iap.egg-info/SOURCES.txt
tsl_itunes_iap.egg-info/dependency_links.txt
tsl_itunes_iap.egg-info/requires.txt
tsl_itunes_iap.egg-info/top_level.txt