Metadata-Version: 1.1
Name: tsl-itunes-iap
Version: 0.6.6
Summary: Itunes In-app purchase verification api.
Home-page: https://github.com/silverlogic/itunes-iap
Author: Ryan Pineo
Author-email: ry@tsl.io
License: UNKNOWN
Platform: UNKNOWN
Classifier: Intended Audience :: Developers
Classifier: Operating System :: OS Independent
Classifier: Programming Language :: Python
Classifier: Programming Language :: Python :: 2
Classifier: Programming Language :: Python :: 2.6
Classifier: Programming Language :: Python :: 2.7
Classifier: Programming Language :: Python :: 3
Classifier: Programming Language :: Python :: 3.3
Classifier: Programming Language :: Python :: 3.4
